src/__init__.py
src/__main__.py
src/code_suggestions.py
src/config.py
sweepai-3.2.5.dist-info/LICENSE
sweepai-3.2.5.dist-info/METADATA
sweepai-3.2.5.dist-info/WHEEL
sweepai-3.2.5.dist-info/entry_points.txt
sweepai-3.2.5.dist-info/top_level.txt
sweepai-3.2.5.dist-info/RECORD
