Metadata-Version: 2.1
Name: sweepai
Version: 3.2.5
Summary: CLI for syncing with Sweep Chat's code change features.
Author-email: Kevin Lu <kevin@sweep.dev>, William Zeng <william@sweep.dev>, Martin Ye <martin@sweep.dev>
License: Sweep Enterprise Edition (EE) license (the “EE License”)
Project-URL: Repository, https://github.com/sweepai/sweep
Project-URL: Community, https://community.sweep.dev/
Project-URL: Documentation, https://docs.sweep.dev
Project-URL: Homepage, https://sweep.dev
Project-URL: Bug Tracker, https://github.com/sweepai/sweep/issues
Classifier: Programming Language :: Python :: 3.10
Requires-Python: >=3.10
License-File: LICENSE
Requires-Dist: loguru==0.7.2
Requires-Dist: requests==2.32.3
Requires-Dist: rich==13.9.4
Requires-Dist: pydantic==2.9.2
Requires-Dist: python-dotenv==1.0.1
Requires-Dist: typer==0.13.0
